pupil_labs/real_time_screen_gaze/__init__.py
pupil_labs/real_time_screen_gaze/camera_models.py
pupil_labs/real_time_screen_gaze/gaze_mapper.py
pupil_labs/real_time_screen_gaze/marker_generator.py
real_time_screen_gaze-1.1.2.dist-info/LICENSE
real_time_screen_gaze-1.1.2.dist-info/METADATA
real_time_screen_gaze-1.1.2.dist-info/WHEEL
real_time_screen_gaze-1.1.2.dist-info/top_level.txt
real_time_screen_gaze-1.1.2.dist-info/RECORD
