Metadata-Version: 2.1
Name: real_time_screen_gaze
Version: 1.1.2
Summary: Acquire screen-based gaze coordinates in realtime
Home-page: https://github.com/pupil-labs/real_time_screen_gaze
Author: Pupil Labs GmbH
Author-email: info@pupil-labs.com
License: MIT
Classifier: Development Status :: 5 - Production/Stable
Classifier: Intended Audience :: Developers
Classifier: License :: OSI Approved :: MIT License
Classifier: Programming Language :: Python :: 3
Classifier: Programming Language :: Python :: 3 :: Only
Requires-Python: >=3.7
License-File: LICENSE
Requires-Dist: importlib-metadata; python_version < "3.8"
Requires-Dist: pupil_apriltags
Requires-Dist: opencv-contrib-python
Requires-Dist: requests
Requires-Dist: surface-tracker
Provides-Extra: docs
Requires-Dist: jaraco.packaging>=9; extra == "docs"
Requires-Dist: rst.linker>=1.9; extra == "docs"
Requires-Dist: sphinx; extra == "docs"
Provides-Extra: testing
Requires-Dist: pytest>=6; extra == "testing"
Requires-Dist: pytest-checkdocs>=2.4; extra == "testing"
Requires-Dist: pytest-cov; extra == "testing"
Requires-Dist: pytest-enabler>=1.3; extra == "testing"
Requires-Dist: pytest-mypy>=0.9.1; platform_python_implementation != "PyPy" and extra == "testing"
